<Dungeon Type= "Den" Level = "1" ID= " 0" Special= "0" Tileset= "1">
	<Grid X= "5" Y= "0"> 
		<Wall WallType= "1" WallRotation= "3"></Wall>
	</Grid>
	<Grid X= "6" Y= "0"> 
		<Wall WallType= "1" WallRotation= "2"></Wall>
		<FixedNPC >
			<FNPC ID= "1005" QtyMin= "1" QtyMax= "1" Boss= "0"></FNPC>
			<FNPC ID= "1000" QtyMin= "3" QtyMax= "3" Boss= "0"></FNPC>
		</FixedNPC>
		<Effect ID= "1" HLoc= "2" Vloc= "0"></Effect>
	</Grid>
	<Grid X= "5" Y= "1"> 
		<Wall WallType= "5" WallRotation= "0"></Wall>
	</Grid>
	<Grid X= "6" Y= "1"> 
		<Wall WallType= "1" WallRotation= "1"></Wall>
	</Grid>
	<Grid X= "3" Y= "2"> 
		<Wall WallType= "1" WallRotation= "3"></Wall>
	</Grid>
	<Grid X= "4" Y= "2"> 
		<Wall WallType= "4" WallRotation= "1"></Wall>
	</Grid>
	<Grid X= "5" Y= "2"> 
		<Wall WallType= "1" WallRotation= "1"></Wall>
	</Grid>
	<Grid X= "3" Y= "3"> 
		<Wall WallType= "4" WallRotation= "0"></Wall>
	</Grid>
	<Grid X= "2" Y= "4"> 
		<Wall WallType= "1" WallRotation= "3"></Wall>
	</Grid>
	<Grid X= "3" Y= "4"> 
		<Wall WallType= "3" WallRotation= "0"></Wall>
	</Grid>
	<Grid X= "4" Y= "4"> 
		<Wall WallType= "1" WallRotation= "2"></Wall>
	</Grid>
	<Grid X= "0" Y= "5"> 
		<Wall WallType= "2" WallRotation= "3"></Wall>
	</Grid>
	<Grid X= "1" Y= "5"> 
		<Wall WallType= "4" WallRotation= "1"></Wall>
	</Grid>
	<Grid X= "2" Y= "5"> 
		<Wall WallType= "3" WallRotation= "0"></Wall>
		
	</Grid>
	<Grid X= "3" Y= "5"> 
		<Wall WallType= "3" WallRotation= "0"></Wall>
        
		<Obj ID="0" HLoc="5" VLoc="1"></Obj>
		
	</Grid>
	<Grid X= "4" Y= "5"> 
		<Wall WallType= "3" WallRotation= "0"></Wall>
		
	</Grid>
	<Grid X= "5" Y= "5"> 
		<Wall WallType= "2" WallRotation= "1">
			<Collision Type= "1" Direction= "1"> </Collision>
			
		</Wall>
	</Grid>
	<Grid X= "6" Y= "5"> 
		<Wall WallType= "2" WallRotation= "3">
			<Collision Type= "1" Direction= "3"> </Collision>
		</Wall>
	</Grid>
	<Grid X= "7" Y= "5"> 
		<Wall WallType= "4" WallRotation= "1"></Wall>
	</Grid>
	<Grid X= "8" Y= "5"> 
		<Wall WallType= "4" WallRotation= "1"></Wall>
	</Grid>
	<Grid X= "9" Y= "5"> 
		<Wall WallType= "1" WallRotation= "2"></Wall>
	</Grid>
	<Grid X= "11" Y= "5"> 
		<Wall WallType= "1" WallRotation= "3"></Wall>
	</Grid>
	<Grid X= "12" Y= "5"> 
		<Wall WallType= "5" WallRotation= "3"></Wall>
	</Grid>
	<Grid X= "13" Y= "5"> 
		<Wall WallType= "1" WallRotation= "2"></Wall>
		<Effect ID= "2" HLoc= "6" Vloc= "0"></Effect>
	</Grid>
	<Grid X= "2" Y= "6"> 
		<Wall WallType= "1" WallRotation= "0"></Wall>
		<Obj ID="1" HLoc="5" VLoc="1"></Obj>
	</Grid>
	<Grid X= "3" Y= "6"> 
		<Wall WallType= "3" WallRotation= "0"></Wall>
	</Grid>
	<Grid X= "4" Y= "6"> 
		<Wall WallType= "1" WallRotation= "1"></Wall>
	</Grid>
	<Grid X= "9" Y= "6"> 
		<Wall WallType= "4" WallRotation= "0"></Wall>
	</Grid>
	<Grid X= "11" Y= "6"> 
		<Wall WallType= "5" WallRotation= "0"></Wall>
	</Grid>
	<Grid X= "12" Y= "6"> 
		<Wall WallType= "3" WallRotation= "0"></Wall>
	</Grid>
	<Grid X= "13" Y= "6"> 
		<Wall WallType= "5" WallRotation= "2"></Wall>
	</Grid>
	<Grid X= "3" Y= "7"> 
		<Wall WallType= "4" WallRotation= "0"></Wall>
	</Grid>
	<Grid X= "9" Y= "7"> 
		<Wall WallType= "1" WallRotation= "0"></Wall>
	</Grid>
	<Grid X= "10" Y= "7"> 
		<Wall WallType= "2" WallRotation= "1">
			<Collision Type= "1" Direction= "1"> </Collision>
		</Wall>
	</Grid>
	<Grid X= "11" Y= "7"> 
		<Wall WallType= "5" WallRotation= "0">
			<Collision Type= "1" Direction= "3"> </Collision>
		</Wall>
	</Grid>
	<Grid X= "12" Y= "7"> 
		<Wall WallType= "3" WallRotation= "0"></Wall>
	</Grid>
	<Grid X= "13" Y= "7"> 
		<Wall WallType= "5" WallRotation= "2"></Wall>
	</Grid>
	<Grid X= "3" Y= "8"> 
		<Wall WallType= "4" WallRotation= "0"></Wall>
	</Grid>
	<Grid X= "11" Y= "8"> 
		<Wall WallType= "5" WallRotation= "0"></Wall>
	</Grid>
	<Grid X= "12" Y= "8"> 
		<Wall WallType= "3" WallRotation= "0"></Wall>
	</Grid>
	<Grid X= "13" Y= "8"> 
		<Wall WallType= "5" WallRotation= "2"></Wall>
	</Grid>
	<Grid X= "0" Y= "9"> 
		<Wall WallType= "2" WallRotation= "3">
			<Collision Type= "1" Direction= "0"> </Collision>
		</Wall>
	</Grid>
	<Grid X= "1" Y= "9"> 
		<Wall WallType= "4" WallRotation= "1"></Wall>
	</Grid>
	<Grid X= "2" Y= "9"> 
		<Wall WallType= "4" WallRotation= "1"></Wall>
	</Grid>
	<Grid X= "3" Y= "9"> 
		<Wall WallType= "5" WallRotation= "1">
			<Collision Type= "1" Direction= "0"> </Collision>
		</Wall>
	</Grid>
	<Grid X= "4" Y= "9"> 
		<Wall WallType= "4" WallRotation= "1"></Wall>
	</Grid>
	<Grid X= "5" Y= "9"> 
		<Wall WallType= "4" WallRotation= "1"></Wall>
	</Grid>
	<Grid X= "6" Y= "9"> 
		<Wall WallType= "2" WallRotation= "1">
			<Collision Type= "1" Direction= "0"> </Collision>
		</Wall>
	</Grid>
	<Grid X= "11" Y= "9"> 
		<Wall WallType= "1" WallRotation= "0"></Wall>
	</Grid>
	<Grid X= "12" Y= "9"> 
		<Wall WallType= "5" WallRotation= "1"></Wall>
	</Grid>
	<Grid X= "13" Y= "9"> 
		<Wall WallType= "1" WallRotation= "1"></Wall>
	</Grid>
	<Grid X= "0" Y= "10"> 
		<Wall WallType= "2" WallRotation= "2">
			<Collision Type= "1" Direction= "2"> </Collision>
		</Wall>
	</Grid>
	<Grid X= "3" Y= "10"> 
		<Wall WallType= "2" WallRotation= "2">
			<Collision Type= "1" Direction= "2"> </Collision>
		</Wall>
	</Grid>
	<Grid X= "6" Y= "10"> 
		<Wall WallType= "2" WallRotation= "2">
			<Collision Type= "1" Direction= "2"> </Collision>
		</Wall>
	</Grid>
	<Grid X= "0" Y= "11"> 
		<Wall WallType= "5" WallRotation= "0"></Wall>
	</Grid>
	<Grid X= "1" Y= "11"> 
		<Wall WallType= "1" WallRotation= "2"></Wall>
	</Grid>
	<Grid X= "3" Y= "11"> 
		<Wall WallType= "5" WallRotation= "0"></Wall>
	</Grid>
	<Grid X= "4" Y= "11"> 
		<Wall WallType= "1" WallRotation= "2"></Wall>
	</Grid>
	<Grid X= "6" Y= "11"> 
		<Wall WallType= "5" WallRotation= "0"></Wall>
	</Grid>
	<Grid X= "7" Y= "11"> 
		<Wall WallType= "1" WallRotation= "2"></Wall>
	</Grid>

	<Grid X= "0" Y= "12"> 
		<Wall WallType= "1" WallRotation= "0"></Wall>
	</Grid>
	<Grid X= "1" Y= "12"> 
		<Wall WallType= "1" WallRotation= "1"></Wall>
	</Grid>
	<Grid X= "3" Y= "12"> 
		<Wall WallType= "1" WallRotation= "0"></Wall>
	</Grid>
	<Grid X= "4" Y= "12"> 
		<Wall WallType= "1" WallRotation= "1"></Wall>
	</Grid>
	<Grid X= "6" Y= "12"> 
		<Wall WallType= "1" WallRotation= "0"></Wall>
	</Grid>
	<Grid X= "7" Y= "12"> 
		<Wall WallType= "1" WallRotation= "1"></Wall>
	</Grid>
	<RandomNPC MinGroups= "1" MaxGroups= "3">
		<NPC ID= "1000" QtyMin= "1" QtyMax= "4" Boss= "0"></NPC>
		<NPC ID= "1001" QtyMin= "1" QtyMax= "3" Boss= "0"></NPC>
		<NPC ID= "1002" QtyMin= "1" QtyMax= "3" Boss= "0"></NPC>
		<NPC ID= "1003" QtyMin= "1" QtyMax= "2" Boss= "0"></NPC>
		<NPC ID= "1004" QtyMin= "1" QtyMax= "2" Boss= "0"></NPC>
	</RandomNPC>
</Dungeon>


